yieldplotlib/__init__.py
yieldplotlib/_version.py
yieldplotlib/accessibility.py
yieldplotlib/datasets.py
yieldplotlib/generate_docs.py
yieldplotlib/generate_key_map.py
yieldplotlib/key_map.py
yieldplotlib/logger.py
yieldplotlib/pipeline.py
yieldplotlib/util.py
yieldplotlib/ypl_cli.py
yieldplotlib/core/__init__.py
yieldplotlib/core/directory_node.py
yieldplotlib/core/file_nodes.py
yieldplotlib/core/node.py
yieldplotlib/core/single_inputs.py
yieldplotlib/data/logo.png
yieldplotlib/load/__init__.py
yieldplotlib/load/ayo_directory.py
yieldplotlib/load/exosims_directory.py
yieldplotlib/load/yip_directory.py
yieldplotlib/load/ayo/__init__.py
yieldplotlib/load/ayo/ayo_csv.py
yieldplotlib/load/ayo/ayo_input.py
yieldplotlib/load/exosims/__init__.py
yieldplotlib/load/exosims/exosims_csv.py
yieldplotlib/load/exosims/exosims_drm.py
yieldplotlib/load/exosims/exosims_input_file.py
yieldplotlib/load/exosims/exosims_spc.py
yieldplotlib/plots/__init__.py
yieldplotlib/plots/comparison_plots.py
yieldplotlib/plots/generic_plot.py
yieldplotlib/plots/hz_completeness.py
yieldplotlib/plots/yield_hist.py
yieldplotlib/plots/yip_plots.py
yieldplotlib/style/__init__.py
yieldplotlib/style/custom_colors.py
yieldplotlib/style/yieldplotlib.mplstyle
yieldplotlib/style/ypl_style.txt
yieldplotlib-1.1.1.dist-info/METADATA
yieldplotlib-1.1.1.dist-info/WHEEL
yieldplotlib-1.1.1.dist-info/entry_points.txt
yieldplotlib-1.1.1.dist-info/licenses/LICENSE
yieldplotlib-1.1.1.dist-info/RECORD
