Metadata-Version: 2.4
Name: yieldplotlib
Version: 1.1.1
Summary: A Python pipeline to generate plots for exoplanet yield simulations.
Project-URL: Homepage, https://github.com/HWO-Yield-Visualizations/yieldplotlib
Project-URL: Issues, https://github.com/HWO-Yield-Visualizations/yieldplotlib/issues
Author-email: Corey Spohn <corey.a.spohn@nasa.gov>, Sarah Steiger <ssteiger@stsci.edu>
License: MIT License
License-File: LICENSE
Classifier: Intended Audience :: Science/Research
Classifier: License :: OSI Approved :: MIT License
Classifier: Programming Language :: Python :: 3
Classifier: Topic :: Scientific/Engineering :: Astronomy
Requires-Python: >=3.10
Requires-Dist: astropy
Requires-Dist: colorspacious
Requires-Dist: docopt
Requires-Dist: exosims
Requires-Dist: lod-unit>=1.6.0
Requires-Dist: matplotlib
Requires-Dist: mplcyberpunk
Requires-Dist: pooch
Requires-Dist: pyparsing>=3.1.4
Requires-Dist: scipy<1.15
Requires-Dist: synphot
Requires-Dist: tqdm
Requires-Dist: yippy
Provides-Extra: docs
Requires-Dist: itables; extra == 'docs'
Requires-Dist: matplotlib; extra == 'docs'
Requires-Dist: myst-nb; extra == 'docs'
Requires-Dist: sphinx; extra == 'docs'
Requires-Dist: sphinx-autoapi; extra == 'docs'
Requires-Dist: sphinx-autodoc-typehints; extra == 'docs'
Requires-Dist: sphinx-book-theme; extra == 'docs'
Provides-Extra: test
Requires-Dist: nox; extra == 'test'
Requires-Dist: pytest; extra == 'test'
Requires-Dist: pytest-cov; extra == 'test'
